{
  "uuid": "b6517449-8ec9-4184-85c5-93ad9453284a",
  "name": "The Dawson 39",
  "website": "https://www.dawson39.com/",
  "found": true,
  "saved_files": [
    {
      "url": "https://www.dawson39.com/menu#lunch",
      "file": "menus/the-dawson-39--b6517449/lunch-specials.html",
      "status": 200,
      "content_type": "text/html",
      "is_menu_like": true
    },
    {
      "url": "https://www.dawson39.com/menu#drinks",
      "file": "menus/the-dawson-39--b6517449/drinks-menu.html",
      "status": 200,
      "content_type": "text/html",
      "is_menu_like": true
    },
    {
      "url": "https://www.dawson39.com/",
      "file": "menus/the-dawson-39--b6517449/menu.html",
      "status": 200,
      "content_type": "text/html",
      "is_menu_like": true
    },
    {
      "url": "https://www.dawson39.com/menu.html",
      "file": "menus/the-dawson-39--b6517449/all-day.html",
      "status": 200,
      "content_type": "text/html",
      "is_menu_like": true
    }
  ],
  "errors": []
}