{
  "uuid": "9dc9b7bc-a45a-4da1-8f3f-e128b96d3bef",
  "name": "Applejack Diner",
  "website": "https://www.applejackdiner.com/",
  "timestamp": "2025-12-06T20:31:41.362508+00:00",
  "found": true,
  "saved_files": [
    {
      "url": "https://www.applejackdiner.com/menu/",
      "file": "menus/applejack-diner--9dc9b7bc/view-our-menu.html",
      "status": 200,
      "content_type": "text/html",
      "is_menu_like": true
    },
    {
      "url": "https://www.applejackdiner.com/",
      "file": "menus/applejack-diner--9dc9b7bc/menu.html",
      "status": 200,
      "content_type": "text/html",
      "is_menu_like": true
    }
  ],
  "errors": []
}