{
  "uuid": "",
  "name": "La Nonna's Pizza",
  "website": "https://lanonnaspizzeria.com/",
  "timestamp": "2025-12-06T22:25:26.646754+00:00",
  "found": true,
  "saved_files": [
    {
      "url": "http://lanonnaspizzeria.com/menu/",
      "file": "menus/la-nonna-s-pizza/see-our-menu.html",
      "status": 200,
      "content_type": "text/html",
      "is_menu_like": true
    },
    {
      "url": "https://lanonnaspizzeria.com/",
      "file": "menus/la-nonna-s-pizza/menu.html",
      "status": 200,
      "content_type": "text/html",
      "is_menu_like": true
    }
  ],
  "errors": []
}