{
  "uuid": "6f6b526a-113f-4bdd-b38e-6f8cf54fcba5",
  "name": "Cozy Cottage Restaurant",
  "website": "http://cozycottagerestaurant.com/",
  "timestamp": "2025-12-06T14:28:56.792727+00:00",
  "found": true,
  "saved_files": [
    {
      "url": "http://cozycottagerestaurant.com/menus/",
      "file": "menus/cozy-cottage-restaurant--6f6b526a/menus.html",
      "status": 200,
      "content_type": "text/html",
      "is_menu_like": true
    },
    {
      "url": "http://cozycottagerestaurant.com/",
      "file": "menus/cozy-cottage-restaurant--6f6b526a/menu.html",
      "status": 200,
      "content_type": "text/html",
      "is_menu_like": true
    }
  ],
  "errors": []
}