{
  "uuid": "41b8de22-a6e9-45c9-917a-502a698ce26f",
  "name": "Katz's Delicatessen",
  "website": "https://www.katzsdelicatessen.com",
  "timestamp": "2025-12-06T20:34:44.417592+00:00",
  "found": true,
  "saved_files": [
    {
      "url": "https://localmenu.katzsdelicatessen.com/menu-and-local/dinner-for-two-package.html",
      "file": "menus/katz-s-delicatessen--41b8de22/dinner-for-two-package-html.html",
      "status": 200,
      "content_type": "text/html",
      "is_menu_like": true
    },
    {
      "url": "https://localmenu.katzsdelicatessen.com/menu-and-local/cheese-blintzes-1.html",
      "file": "menus/katz-s-delicatessen--41b8de22/cheese-blintzes-1-html.html",
      "status": 200,
      "content_type": "text/html",
      "is_menu_like": true
    },
    {
      "url": "https://localmenu.katzsdelicatessen.com/menu-and-local/matzoh-ball-soup.html",
      "file": "menus/katz-s-delicatessen--41b8de22/matzoh-ball-soup-html.html",
      "status": 200,
      "content_type": "text/html",
      "is_menu_like": true
    },
    {
      "url": "https://localmenu.katzsdelicatessen.com/dinner-for-two-package.html",
      "file": "menus/katz-s-delicatessen--41b8de22/dinner-for-two-package-html.html",
      "status": 200,
      "content_type": "text/html",
      "is_menu_like": true
    },
    {
      "url": "https://www.katzsdelicatessen.com",
      "file": "menus/katz-s-delicatessen--41b8de22/menu.html",
      "status": 200,
      "content_type": "text/html",
      "is_menu_like": true
    }
  ],
  "errors": []
}