{
  "uuid": "f2960d7e-ccb5-4cd7-9e3f-ffd30cd03c88",
  "name": "China Star",
  "website": "https://www.chinastarnj.com/",
  "timestamp": "2025-12-08T11:23:51.840027+00:00",
  "found": true,
  "saved_files": [
    {
      "url": "https://www.chinastarnj.com/order/main",
      "file": "menus\\china-star--f2960d7e\\main.html",
      "status": 200,
      "content_type": "text/html",
      "is_menu_like": true
    },
    {
      "url": "https://www.chinastarnj.com/",
      "file": "menus\\china-star--f2960d7e\\menu.html",
      "status": 200,
      "content_type": "text/html",
      "is_menu_like": true
    },
    {
      "url": "https://www.chinastarnj.com/order/main/american-food",
      "file": "menus\\china-star--f2960d7e\\american-food-11.html",
      "status": 200,
      "content_type": "text/html",
      "is_menu_like": true
    },
    {
      "url": "https://www.chinastarnj.com/order/main/seafood",
      "file": "menus\\china-star--f2960d7e\\seafood-10.html",
      "status": 200,
      "content_type": "text/html",
      "is_menu_like": true
    },
    {
      "url": "https://www.chinastarnj.com/order/main/lunch-specials",
      "file": "menus\\china-star--f2960d7e\\lunch-specials-57.html",
      "status": 200,
      "content_type": "text/html",
      "is_menu_like": true
    }
  ],
  "errors": []
}