{
  "uuid": "0297191f-22b3-4cb0-9f10-9300113cfa19",
  "name": "Mizu",
  "website": "https://www.mizufarmingdale.com/",
  "timestamp": "2025-12-08T11:27:46.332626+00:00",
  "found": true,
  "saved_files": [
    {
      "url": "https://www.mizufarmingdale.com/order/main",
      "file": "menus\\mizu--0297191f\\main.html",
      "status": 200,
      "content_type": "text/html",
      "is_menu_like": true
    },
    {
      "url": "https://www.mizufarmingdale.com/",
      "file": "menus\\mizu--0297191f\\menu.html",
      "status": 200,
      "content_type": "text/html",
      "is_menu_like": true
    },
    {
      "url": "https://www.mizufarmingdale.com/order/main/dinner-bento-box",
      "file": "menus\\mizu--0297191f\\dinner-bento-box-6.html",
      "status": 200,
      "content_type": "text/html",
      "is_menu_like": true
    },
    {
      "url": "https://www.mizufarmingdale.com/order/main/dinner-maki-roll",
      "file": "menus\\mizu--0297191f\\dinner-maki-roll-1.html",
      "status": 200,
      "content_type": "text/html",
      "is_menu_like": true
    },
    {
      "url": "https://www.mizufarmingdale.com/order/main/lunch-bento-box",
      "file": "menus\\mizu--0297191f\\lunch-bento-box-10.html",
      "status": 200,
      "content_type": "text/html",
      "is_menu_like": true
    }
  ],
  "errors": []
}