{
  "uuid": "76e25232-6edb-44e7-8340-5735c53336b4",
  "name": "South Slope Ramen",
  "website": "https://www.southsloperamen.com",
  "found": true,
  "saved_files": [
    {
      "url": "https://order.southsloperamen.com/order",
      "file": "menus/south-slope-ramen--76e25232/tools-kitchen-serving-dome-view-full-menu.html",
      "status": 200,
      "content_type": "text/html",
      "is_menu_like": true
    },
    {
      "url": "https://www.southsloperamen.com",
      "file": "menus/south-slope-ramen--76e25232/menu.html",
      "status": 200,
      "content_type": "text/html",
      "is_menu_like": true
    },
    {
      "url": "https://www.southsloperamen.com/#menu",
      "file": "menus/south-slope-ramen--76e25232/menu.html",
      "status": 200,
      "content_type": "text/html",
      "is_menu_like": true
    }
  ],
  "errors": []
}